{
  "$schema": "https://json-schema.org/draft/2020-12/schema#",
  "$id": "resource:/schemas/pst-range-action/pst-range-action-v1.7.json",
  "type": "object",
  "properties": {
    "id": {
      "type": "string"
    },
    "name": {
      "type": [
        "string",
        "null"
      ]
    },
    "operator": {
      "type": [
        "string",
        "null"
      ]
    },
    "groupId": {
      "type": [
        "string",
        "null"
      ]
    },
    "speed": {
      "type": "number"
    },
    "networkElementId": {
      "type": "string"
    },
    "initialTap": {
      "type": "number"
    },
    "tapToAngleConversionMap": {
      "type": "object",
      "additionalProperties": {
        "type": "number"
      }
    },
    "ranges": {
      "type": "array",
      "items": {
        "type": "object",
        "properties": {
          "rangeType": {
            "$ref": "resource:/schemas/range-type/range-type-v1.0.json"
          },
          "max": {
            "type": "number"
          },
          "min": {
            "type": "number"
          }
        },
        "additionalProperties": false,
        "required": [
          "rangeType"
        ]
      }
    },
    "onInstantUsageRules": {
      "type": "array",
      "items": {
        "$ref": "resource:/schemas/on-instant-usage-rule/on-instant-usage-rule-v1.6.json"
      }
    },
    "onContingencyStateUsageRules": {
      "type": "array",
      "items": {
        "$ref": "resource:/schemas/on-contingency-state-usage-rule/on-contingency-state-usage-rule-v1.6.json"
      }
    },
    "onFlowConstraintUsageRules": {
      "type": "array",
      "items": {
        "$ref": "resource:/schemas/on-flow-constraint-usage-rule/on-flow-constraint-usage-rule-v1.0.json"
      }
    },
    "onAngleConstraintUsageRules": {
      "type": "array",
      "items": {
        "$ref": "resource:/schemas/on-angle-constraint-usage-rule/on-angle-constraint-usage-rule-v1.4.json"
      }
    },
    "onVoltageConstraintUsageRules": {
      "type": "array",
      "items": {
        "$ref": "resource:/schemas/on-voltage-constraint-usage-rule/on-voltage-constraint-usage-rule-v1.7.json"
      }
    },
    "onFlowConstraintInCountryUsageRules": {
      "type": "array",
      "items": {
        "$ref": "resource:/schemas/on-flow-constraint-in-country-usage-rule/on-flow-constraint-in-country-usage-rule-v1.3.json"
      }
    }
  },
  "additionalProperties": false,
  "required": [
    "id",
    "networkElementId",
    "ranges"
  ]
}
